nonebot_plugin_dida/__init__.py
nonebot_plugin_dida/config.py
nonebot_plugin_dida/file/source/changelog.md
nonebot_plugin_dida/file/source/column.md
nonebot_plugin_dida/file/source/project.md
nonebot_plugin_dida/file/source/task.md
nonebot_plugin_dida/file/template/task.json
nonebot_plugin_dida/file/template/updateTask.json
nonebot_plugin_dida-2.0.0.1.dist-info/LICENSE
nonebot_plugin_dida-2.0.0.1.dist-info/METADATA
nonebot_plugin_dida-2.0.0.1.dist-info/WHEEL
nonebot_plugin_dida-2.0.0.1.dist-info/top_level.txt
nonebot_plugin_dida-2.0.0.1.dist-info/RECORD
